LICENSE.txt
MANIFEST.in
README.md
TODO.md
requirements-py2.txt
requirements-tests.txt
requirements.txt
setup.cfg
setup.py
hacheck/__init__.py
hacheck/cache.py
hacheck/checker.py
hacheck/compat.py
hacheck/config.py
hacheck/handlers.py
hacheck/haupdown.py
hacheck/main.py
hacheck/mysql.py
hacheck/spool.py
hacheck.egg-info/PKG-INFO
hacheck.egg-info/SOURCES.txt
hacheck.egg-info/dependency_links.txt
hacheck.egg-info/entry_points.txt
hacheck.egg-info/requires.txt
hacheck.egg-info/top_level.txt