Metadata-Version: 1.1
Name: hacheck
Version: 0.7.0
Summary: HAProxy health-check proxying service
Home-page: https://github.com/uber/hacheck
Author: James Brown
Author-email: jbrown@uber.com
License: MIT
Keywords: monitoring,load-balancing,networking
Platform: UNKNOWN
Classifier: Development Status :: 3 - Alpha
Classifier: Environment :: Web Environment
Classifier: Programming Language :: Python
Classifier: Programming Language :: Python :: 2.7
Classifier: Programming Language :: Python :: 3.2
Classifier: Programming Language :: Python :: 3.3
Classifier: Programming Language :: Python :: 3.4
Classifier: Intended Audience :: Developers
Classifier: Operating System :: OS Independent
Classifier: License :: OSI Approved :: MIT License
Classifier: Topic :: System :: Monitoring
